pobd/__init__.py
pobd/api/__init__.py
pobd/api/ocr.py
pobd/api/ocr2excel.py
pobd/core/Baidu.py
pobd/core/__init__.py
pobd-0.0.3.dist-info/licenses/LICENSE
tests/__init__.py
tests/test_codes/__init__.py
tests/test_codes/test_ocr.py
tests/test_codes/test_ocr2excel.py
pobd-0.0.3.dist-info/METADATA
pobd-0.0.3.dist-info/WHEEL
pobd-0.0.3.dist-info/top_level.txt
pobd-0.0.3.dist-info/RECORD
