Metadata-Version: 2.4
Name: pobd
Version: 0.0.3
Summary: pip install pobd
Home-page: https://www.python-office.com/
Author: CoderWanFeng、YaaaKaaang
Author-email: 1957875073@qq.com、1639972003@qq.com
License: MIT
Project-URL: Bug Tracker, https://gitcode.com/python4office/pobd/issues
Project-URL: Documentation, https://gitcode.com/python4office/pobd/blob/master/README.md
Project-URL: Source Code, https://gitcode.com/python4office/pobd
Platform: any
Requires-Python: >=3.7
License-File: LICENSE
Requires-Dist: requests
Requires-Dist: pandas
Requires-Dist: openpyxl
Requires-Dist: toml
Requires-Dist: pofile
Requires-Dist: loguru
Requires-Dist: baidu-aip
Requires-Dist: chardet
Dynamic: license-file
